MANIFEST.in
README.rst
manage.py
requirements.txt
setup.cfg
setup.py
dist/varapp-backend-py-1.0.1.2/varapp/filters/apply_bitwise.pyx
resources/__init__.py
resources/db/demo_mini.db
resources/dumps/init/demo_data.json
varapp/__init__.py
varapp/apps.py
varapp/routers.py
varapp/urls.py
varapp/annotation/__init__.py
varapp/annotation/annotation_service.py
varapp/annotation/genomic_range.py
varapp/annotation/location_service.py
varapp/auth/__init__.py
varapp/auth/auth.py
varapp/common/__init__.py
varapp/common/db_utils.py
varapp/common/email.py
varapp/common/gemini.py
varapp/common/genotypes.py
varapp/common/manage_dbs.py
varapp/common/masking.py
varapp/common/utils.py
varapp/common/versioning.py
varapp/common/cache/__init__.py
varapp/common/cache/locmem_cache.py
varapp/common/cache/redis.py
varapp/constants/__init__.py
varapp/constants/common.py
varapp/constants/filters.py
varapp/constants/genotype.py
varapp/constants/roles.py
varapp/constants/tests.py
varapp/data_models/__init__.py
varapp/data_models/samples.py
varapp/data_models/users.py
varapp/data_models/variants.py
varapp/export/__init__.py
varapp/export/export.py
varapp/filters/__init__.py
varapp/filters/apply_bitwise.c
varapp/filters/apply_bitwise.pyx
varapp/filters/filters.py
varapp/filters/filters_factory.py
varapp/filters/genotype_filters.py
varapp/filters/pagination.py
varapp/filters/sort.py
varapp/filters/variant_filters.py
varapp/history/__init__.py
varapp/history/bookmarks.py
varapp/migrations/0001_squashed_0003_auto_20160303_0946.py
varapp/migrations/0002_auto_20160315_1401.py
varapp/migrations/0003_auto_20160317_1100.py
varapp/migrations/0004_auto_20160517_1454.py
varapp/migrations/0005_auto_20160523_1357.py
varapp/migrations/0006_auto_20160609_1710.py
varapp/migrations/__init__.py
varapp/models/__init__.py
varapp/models/gemini.py
varapp/models/users.py
varapp/samples/__init__.py
varapp/samples/samples_factory.py
varapp/samples/samples_service.py
varapp/stats/__init__.py
varapp/stats/histograms.py
varapp_backend_py.egg-info/PKG-INFO
varapp_backend_py.egg-info/SOURCES.txt
varapp_backend_py.egg-info/dependency_links.txt
varapp_backend_py.egg-info/requires.txt
varapp_backend_py.egg-info/top_level.txt
