Metadata-Version: 1.1
Name: varapp-backend-py
Version: 1.0.1.2
Summary: Genomic variants explorer
Home-page: https://github.com/varapp/varapp-backend-py
Author: Vital-IT/SIB/CHUV
Author-email: julien.delafontaine@sib.swiss
License: GPL-3
Download-URL: https://github.com/varapp/varapp-backend-py/tarball/1.0.1.2
Keywords: variants,filter,genotype,gemini
Platform: UNKNOWN
Classifier: Environment :: Web Environment
Classifier: Framework :: Django
Classifier: Intended Audience :: Developers
Classifier: License :: OSI Approved :: GNU General Public License v3 (GPLv3)
Classifier: Operating System :: OS Independent
Classifier: Programming Language :: Python
Classifier: Programming Language :: Python :: 3
Classifier: Topic :: Internet :: WWW/HTTP
Classifier: Topic :: Internet :: WWW/HTTP :: Dynamic Content
